[
    {
    "nastavnik": {
    "username": "Naida",
    "password_hash": "123"
    },
    "predmeti": [
    "Razvoj mobilnih aplikacija",
    "Osnove informacionih istrazivanja",
    "Razvoj programskih rjesenja"
    ]
    },
    {
    "nastavnik": {
    "username": "Adem",
    "password_hash": "123"
    },
    "predmeti": [
    "Web tehnologije"
    ]
    },
    {
    "nastavnik": {
    "username": "Lajla",
    "password_hash": "123"
    },
    "predmeti": [
    "Razvoj programskih rjesenja"
    ]
    }
]
    